{
  "version": "1.0",
  "description": "香港中學課程知識點種子數據（S1-S6）",
  "points": [
    {
      "subject": "chinese",
      "category": "閱讀理解",
      "point_code": "chi_reading",
      "point_name": "閱讀理解",
      "description": "中文閱讀理解能力",
      "grade_levels": ["S1","S2","S3","S4","S5","S6"],
      "parent_code": null,
      "difficulty_level": 1,
      "display_order": 1
    },
    {
      "subject": "chinese",
      "category": "閱讀理解",
      "point_code": "chi_reading_narrative",
      "point_name": "記敘文理解",
      "description": "理解記敘文的人物、事件、情節發展",
      "grade_levels": ["S1","S2","S3"],
      "parent_code": "chi_reading",
      "difficulty_level": 2,
      "display_order": 1
    },
    {
      "subject": "chinese",
      "category": "閱讀理解",
      "point_code": "chi_reading_expository",
      "point_name": "說明文理解",
      "description": "理解說明文的結構、說明方法和主旨",
      "grade_levels": ["S1","S2","S3","S4"],
      "parent_code": "chi_reading",
      "difficulty_level": 2,
      "display_order": 2
    },
    {
      "subject": "chinese",
      "category": "閱讀理解",
      "point_code": "chi_reading_argumentative",
      "point_name": "議論文理解",
      "description": "辨識議論文的論點、論據和論證方法",
      "grade_levels": ["S3","S4","S5","S6"],
      "parent_code": "chi_reading",
      "difficulty_level": 3,
      "display_order": 3
    },
    {
      "subject": "chinese",
      "category": "閱讀理解",
      "point_code": "chi_reading_classical",
      "point_name": "文言文閱讀",
      "description": "文言文字詞解釋、句式分析、內容理解",
      "grade_levels": ["S2","S3","S4","S5","S6"],
      "parent_code": "chi_reading",
      "difficulty_level": 4,
      "display_order": 4
    },
    {
      "subject": "chinese",
      "category": "閱讀理解",
      "point_code": "chi_reading_poetry",
      "point_name": "詩詞鑑賞",
      "description": "古詩詞的意境、修辭、主題分析",
      "grade_levels": ["S3","S4","S5","S6"],
      "parent_code": "chi_reading",
      "difficulty_level": 4,
      "display_order": 5
    },
    {
      "subject": "chinese",
      "category": "寫作",
      "point_code": "chi_writing",
      "point_name": "寫作",
      "description": "中文寫作能力",
      "grade_levels": ["S1","S2","S3","S4","S5","S6"],
      "parent_code": null,
      "difficulty_level": 1,
      "display_order": 2
    },
    {
      "subject": "chinese",
      "category": "寫作",
      "point_code": "chi_writing_narrative",
      "point_name": "記敘文寫作",
      "description": "記敘文的結構、人物描寫、敘述技巧",
      "grade_levels": ["S1","S2","S3"],
      "parent_code": "chi_writing",
      "difficulty_level": 2,
      "display_order": 1
    },
    {
      "subject": "chinese",
      "category": "寫作",
      "point_code": "chi_writing_argumentative",
      "point_name": "議論文寫作",
      "description": "議論文的立論、論證、反駁技巧",
      "grade_levels": ["S4","S5","S6"],
      "parent_code": "chi_writing",
      "difficulty_level": 4,
      "display_order": 2
    },
    {
      "subject": "chinese",
      "category": "寫作",
      "point_code": "chi_writing_description",
      "point_name": "描寫技巧",
      "description": "人物描寫、景物描寫、細節描寫",
      "grade_levels": ["S1","S2","S3","S4"],
      "parent_code": "chi_writing",
      "difficulty_level": 2,
      "display_order": 3
    },
    {
      "subject": "chinese",
      "category": "寫作",
      "point_code": "chi_writing_rhetoric",
      "point_name": "修辭手法",
      "description": "比喻、擬人、排比、誇張等修辭運用",
      "grade_levels": ["S1","S2","S3","S4","S5","S6"],
      "parent_code": "chi_writing",
      "difficulty_level": 3,
      "display_order": 4
    },
    {
      "subject": "chinese",
      "category": "寫作",
      "point_code": "chi_writing_structure",
      "point_name": "文章結構",
      "description": "開頭結尾、段落安排、過渡銜接",
      "grade_levels": ["S2","S3","S4","S5","S6"],
      "parent_code": "chi_writing",
      "difficulty_level": 3,
      "display_order": 5
    },
    {
      "subject": "chinese",
      "category": "語文基礎",
      "point_code": "chi_foundation",
      "point_name": "語文基礎",
      "description": "語文基礎知識",
      "grade_levels": ["S1","S2","S3","S4","S5","S6"],
      "parent_code": null,
      "difficulty_level": 1,
      "display_order": 3
    },
    {
      "subject": "chinese",
      "category": "語文基礎",
      "point_code": "chi_vocab",
      "point_name": "字詞運用",
      "description": "詞語辨析、近義詞反義詞、詞語搭配",
      "grade_levels": ["S1","S2","S3"],
      "parent_code": "chi_foundation",
      "difficulty_level": 2,
      "display_order": 1
    },
    {
      "subject": "chinese",
      "category": "語文基礎",
      "point_code": "chi_grammar",
      "point_name": "語法知識",
      "description": "句子成分、語病修改、句式轉換",
      "grade_levels": ["S1","S2","S3","S4"],
      "parent_code": "chi_foundation",
      "difficulty_level": 2,
      "display_order": 2
    },
    {
      "subject": "chinese",
      "category": "語文基礎",
      "point_code": "chi_punctuation",
      "point_name": "標點符號",
      "description": "標點符號的正確使用",
      "grade_levels": ["S1","S2"],
      "parent_code": "chi_foundation",
      "difficulty_level": 1,
      "display_order": 3
    },
    {
      "subject": "chinese",
      "category": "語文基礎",
      "point_code": "chi_idiom",
      "point_name": "成語運用",
      "description": "成語的理解和正確運用",
      "grade_levels": ["S2","S3","S4","S5","S6"],
      "parent_code": "chi_foundation",
      "difficulty_level": 3,
      "display_order": 4
    },

    {
      "subject": "math",
      "category": "數與代數",
      "point_code": "math_algebra",
      "point_name": "數與代數",
      "description": "代數相關知識",
      "grade_levels": ["S1","S2","S3","S4","S5","S6"],
      "parent_code": null,
      "difficulty_level": 1,
      "display_order": 1
    },
    {
      "subject": "math",
      "category": "數與代數",
      "point_code": "math_rational",
      "point_name": "有理數運算",
      "description": "正負數、分數、小數的四則運算",
      "grade_levels": ["S1","S2"],
      "parent_code": "math_algebra",
      "difficulty_level": 1,
      "display_order": 1
    },
    {
      "subject": "math",
      "category": "數與代數",
      "point_code": "math_expression",
      "point_name": "代數式",
      "description": "代數式的化簡、因式分解、展開",
      "grade_levels": ["S1","S2","S3"],
      "parent_code": "math_algebra",
      "difficulty_level": 2,
      "display_order": 2
    },
    {
      "subject": "math",
      "category": "數與代數",
      "point_code": "math_linear_eq",
      "point_name": "一元方程",
      "description": "一元一次方程、一元二次方程的解法與應用",
      "grade_levels": ["S1","S2","S3"],
      "parent_code": "math_algebra",
      "difficulty_level": 2,
      "display_order": 3
    },
    {
      "subject": "math",
      "category": "數與代數",
      "point_code": "math_quadratic",
      "point_name": "二次方程",
      "description": "二次方程的解法、判別式、根與係數的關係",
      "grade_levels": ["S3","S4"],
      "parent_code": "math_algebra",
      "difficulty_level": 3,
      "display_order": 4
    },
    {
      "subject": "math",
      "category": "數與代數",
      "point_code": "math_inequality",
      "point_name": "不等式",
      "description": "一元一次不等式、二次不等式",
      "grade_levels": ["S2","S3","S4"],
      "parent_code": "math_algebra",
      "difficulty_level": 3,
      "display_order": 5
    },
    {
      "subject": "math",
      "category": "數與代數",
      "point_code": "math_function",
      "point_name": "函數",
      "description": "函數概念、一次函數、二次函數、指數對數函數",
      "grade_levels": ["S3","S4","S5","S6"],
      "parent_code": "math_algebra",
      "difficulty_level": 4,
      "display_order": 6
    },
    {
      "subject": "math",
      "category": "數與代數",
      "point_code": "math_sequence",
      "point_name": "數列",
      "description": "等差數列、等比數列、求和",
      "grade_levels": ["S4","S5","S6"],
      "parent_code": "math_algebra",
      "difficulty_level": 4,
      "display_order": 7
    },
    {
      "subject": "math",
      "category": "幾何",
      "point_code": "math_geometry",
      "point_name": "幾何",
      "description": "幾何相關知識",
      "grade_levels": ["S1","S2","S3","S4","S5","S6"],
      "parent_code": null,
      "difficulty_level": 1,
      "display_order": 2
    },
    {
      "subject": "math",
      "category": "幾何",
      "point_code": "math_plane_geo",
      "point_name": "平面幾何",
      "description": "三角形、四邊形、圓的性質與定理",
      "grade_levels": ["S1","S2","S3","S4"],
      "parent_code": "math_geometry",
      "difficulty_level": 3,
      "display_order": 1
    },
    {
      "subject": "math",
      "category": "幾何",
      "point_code": "math_coord_geo",
      "point_name": "坐標幾何",
      "description": "直線方程、斜率、距離公式、圓的方程",
      "grade_levels": ["S3","S4","S5"],
      "parent_code": "math_geometry",
      "difficulty_level": 3,
      "display_order": 2
    },
    {
      "subject": "math",
      "category": "幾何",
      "point_code": "math_trigonometry",
      "point_name": "三角學",
      "description": "三角比、三角恆等式、解三角形",
      "grade_levels": ["S3","S4","S5","S6"],
      "parent_code": "math_geometry",
      "difficulty_level": 4,
      "display_order": 3
    },
    {
      "subject": "math",
      "category": "幾何",
      "point_code": "math_solid_geo",
      "point_name": "立體幾何",
      "description": "立體的體積、表面積、截面",
      "grade_levels": ["S2","S3","S4"],
      "parent_code": "math_geometry",
      "difficulty_level": 3,
      "display_order": 4
    },
    {
      "subject": "math",
      "category": "統計與概率",
      "point_code": "math_stats",
      "point_name": "統計與概率",
      "description": "統計與概率知識",
      "grade_levels": ["S1","S2","S3","S4","S5","S6"],
      "parent_code": null,
      "difficulty_level": 1,
      "display_order": 3
    },
    {
      "subject": "math",
      "category": "統計與概率",
      "point_code": "math_data",
      "point_name": "數據處理",
      "description": "平均數、中位數、眾數、標準差",
      "grade_levels": ["S1","S2","S3"],
      "parent_code": "math_stats",
      "difficulty_level": 2,
      "display_order": 1
    },
    {
      "subject": "math",
      "category": "統計與概率",
      "point_code": "math_charts",
      "point_name": "統計圖表",
      "description": "柱形圖、折線圖、圓形圖、莖葉圖的閱讀與繪製",
      "grade_levels": ["S1","S2","S3"],
      "parent_code": "math_stats",
      "difficulty_level": 2,
      "display_order": 2
    },
    {
      "subject": "math",
      "category": "統計與概率",
      "point_code": "math_probability",
      "point_name": "概率",
      "description": "概率基本概念、條件概率、排列組合",
      "grade_levels": ["S3","S4","S5","S6"],
      "parent_code": "math_stats",
      "difficulty_level": 3,
      "display_order": 3
    },

    {
      "subject": "english",
      "category": "Grammar",
      "point_code": "eng_grammar",
      "point_name": "Grammar",
      "description": "English grammar knowledge",
      "grade_levels": ["S1","S2","S3","S4","S5","S6"],
      "parent_code": null,
      "difficulty_level": 1,
      "display_order": 1
    },
    {
      "subject": "english",
      "category": "Grammar",
      "point_code": "eng_tenses",
      "point_name": "Tenses 時態",
      "description": "Present/Past/Future tenses, Perfect tenses, Continuous tenses",
      "grade_levels": ["S1","S2","S3","S4"],
      "parent_code": "eng_grammar",
      "difficulty_level": 2,
      "display_order": 1
    },
    {
      "subject": "english",
      "category": "Grammar",
      "point_code": "eng_parts_of_speech",
      "point_name": "Parts of Speech 詞性",
      "description": "Nouns, Verbs, Adjectives, Adverbs, Prepositions, Conjunctions",
      "grade_levels": ["S1","S2","S3"],
      "parent_code": "eng_grammar",
      "difficulty_level": 2,
      "display_order": 2
    },
    {
      "subject": "english",
      "category": "Grammar",
      "point_code": "eng_sentence_structure",
      "point_name": "Sentence Structure 句子結構",
      "description": "Simple, Compound, Complex sentences; Active/Passive voice",
      "grade_levels": ["S2","S3","S4","S5"],
      "parent_code": "eng_grammar",
      "difficulty_level": 3,
      "display_order": 3
    },
    {
      "subject": "english",
      "category": "Grammar",
      "point_code": "eng_agreement",
      "point_name": "Subject-Verb Agreement 主謂一致",
      "description": "Subject-verb agreement rules and exceptions",
      "grade_levels": ["S1","S2","S3"],
      "parent_code": "eng_grammar",
      "difficulty_level": 2,
      "display_order": 4
    },
    {
      "subject": "english",
      "category": "Grammar",
      "point_code": "eng_conditionals",
      "point_name": "Conditionals 條件句",
      "description": "Zero, First, Second, Third conditionals; Mixed conditionals",
      "grade_levels": ["S3","S4","S5","S6"],
      "parent_code": "eng_grammar",
      "difficulty_level": 4,
      "display_order": 5
    },
    {
      "subject": "english",
      "category": "Grammar",
      "point_code": "eng_modals",
      "point_name": "Modal Verbs 情態動詞",
      "description": "Can, Could, May, Might, Must, Should, Would usage",
      "grade_levels": ["S1","S2","S3","S4"],
      "parent_code": "eng_grammar",
      "difficulty_level": 2,
      "display_order": 6
    },
    {
      "subject": "english",
      "category": "Reading",
      "point_code": "eng_reading",
      "point_name": "Reading 閱讀",
      "description": "English reading skills",
      "grade_levels": ["S1","S2","S3","S4","S5","S6"],
      "parent_code": null,
      "difficulty_level": 1,
      "display_order": 2
    },
    {
      "subject": "english",
      "category": "Reading",
      "point_code": "eng_comprehension",
      "point_name": "Reading Comprehension 閱讀理解",
      "description": "Main idea, supporting details, author's purpose",
      "grade_levels": ["S1","S2","S3","S4","S5","S6"],
      "parent_code": "eng_reading",
      "difficulty_level": 3,
      "display_order": 1
    },
    {
      "subject": "english",
      "category": "Reading",
      "point_code": "eng_vocab_context",
      "point_name": "Vocabulary in Context 語境詞彙",
      "description": "Understanding word meaning from context clues",
      "grade_levels": ["S1","S2","S3","S4","S5","S6"],
      "parent_code": "eng_reading",
      "difficulty_level": 3,
      "display_order": 2
    },
    {
      "subject": "english",
      "category": "Reading",
      "point_code": "eng_inference",
      "point_name": "Inference 推斷",
      "description": "Making inferences and drawing conclusions from text",
      "grade_levels": ["S3","S4","S5","S6"],
      "parent_code": "eng_reading",
      "difficulty_level": 4,
      "display_order": 3
    },
    {
      "subject": "english",
      "category": "Writing",
      "point_code": "eng_writing",
      "point_name": "Writing 寫作",
      "description": "English writing skills",
      "grade_levels": ["S1","S2","S3","S4","S5","S6"],
      "parent_code": null,
      "difficulty_level": 1,
      "display_order": 3
    },
    {
      "subject": "english",
      "category": "Writing",
      "point_code": "eng_essay_structure",
      "point_name": "Essay Structure 文章結構",
      "description": "Introduction, Body paragraphs, Conclusion; Topic sentences",
      "grade_levels": ["S2","S3","S4","S5","S6"],
      "parent_code": "eng_writing",
      "difficulty_level": 3,
      "display_order": 1
    },
    {
      "subject": "english",
      "category": "Writing",
      "point_code": "eng_register",
      "point_name": "Formal/Informal Register 語域",
      "description": "Formal and informal language; Appropriate register for context",
      "grade_levels": ["S3","S4","S5","S6"],
      "parent_code": "eng_writing",
      "difficulty_level": 3,
      "display_order": 2
    },
    {
      "subject": "english",
      "category": "Writing",
      "point_code": "eng_cohesion",
      "point_name": "Cohesion & Coherence 連貫性",
      "description": "Linking words, transitions, paragraph coherence",
      "grade_levels": ["S3","S4","S5","S6"],
      "parent_code": "eng_writing",
      "difficulty_level": 3,
      "display_order": 3
    },
    {
      "subject": "english",
      "category": "Dictation",
      "point_code": "eng_dictation",
      "point_name": "Dictation 默書",
      "description": "Spelling and dictation skills",
      "grade_levels": ["S1","S2","S3","S4"],
      "parent_code": null,
      "difficulty_level": 1,
      "display_order": 4
    },
    {
      "subject": "english",
      "category": "Dictation",
      "point_code": "eng_spelling",
      "point_name": "Spelling 拼寫",
      "description": "Correct spelling of vocabulary words",
      "grade_levels": ["S1","S2","S3","S4"],
      "parent_code": "eng_dictation",
      "difficulty_level": 2,
      "display_order": 1
    },
    {
      "subject": "english",
      "category": "Dictation",
      "point_code": "eng_vocabulary",
      "point_name": "Vocabulary 詞彙",
      "description": "Vocabulary building and word usage",
      "grade_levels": ["S1","S2","S3","S4","S5","S6"],
      "parent_code": "eng_dictation",
      "difficulty_level": 2,
      "display_order": 2
    },
    {
      "subject": "english",
      "category": "Dictation",
      "point_code": "eng_homophones",
      "point_name": "Homophones 同音詞",
      "description": "Distinguishing words that sound alike but differ in meaning/spelling",
      "grade_levels": ["S1","S2","S3"],
      "parent_code": "eng_dictation",
      "difficulty_level": 2,
      "display_order": 3
    }
  ]
}
